Metadata-Version: 1.0
Name: django-builder
Version: 0.1
Summary: Help set up project for Deployment, Docker, Secret key management
Home-page: UNKNOWN
Author: lhy
Author-email: dev@azelf.com
License: MIT
Platform: UNKNOWN
